{
    "2024-04-16": {
        "low": [
            null,
            72.63,
            72.55,
            72.75,
            72.86,
            72.95,
            72.86,
            73.04
        ],
        "high": [
            null,
            72.82,
            72.68,
            72.75,
            72.86,
            72.95,
            72.86,
            73.04
        ],
        "conditions": [
            null,
            [
                "Rain"
            ],
            [
                "Clouds"
            ],
            [
                "Clouds"
            ],
            [
                "Clouds"
            ],
            [
                "Clouds"
            ],
            [
                "Clouds"
            ],
            [
                "Clouds"
            ]
        ],
        "icons": [
            null,
            [
                "10n"
            ],
            [
                "04d"
            ],
            [
                "04d"
            ],
            [
                "04d"
            ],
            [
                "04d"
            ],
            [
                "04d"
            ],
            [
                "04n"
            ]
        ]
    },
    "2024-04-17": {
        "low": [
            null,
            72.64,
            72.57,
            72.91,
            73.13,
            73.29,
            73.13,
            72.91
        ],
        "high": [
            null,
            73.6,
            73.08,
            72.91,
            73.13,
            73.29,
            73.13,
            72.91
        ],
        "conditions": [
            null,
            [
                "Clouds"
            ],
            [
                "Clouds"
            ],
            [
                "Clouds"
            ],
            [
                "Clouds"
            ],
            [
                "Clouds"
            ],
            [
                "Clouds"
            ],
            [
                "Clouds"
            ]
        ],
        "icons": [
            null,
            [
                "04n"
            ],
            [
                "04d"
            ],
            [
                "04d"
            ],
            [
                "04d"
            ],
            [
                "04d"
            ],
            [
                "04d"
            ],
            [
                "04n"
            ]
        ]
    },
    "2024-04-18": {
        "low": [
            73.47,
            73.2,
            73.22,
            73.67,
            73.85,
            73.94,
            73.63,
            73.33
        ],
        "high": [
            73.47,
            73.85,
            73.54,
            73.67,
            73.85,
            73.94,
            73.63,
            73.33
        ],
        "conditions": [
            [
                "Clouds"
            ],
            [
                "Clouds"
            ],
            [
                "Clouds"
            ],
            [
                "Clouds"
            ],
            [
                "Clouds"
            ],
            [
                "Clouds"
            ],
            [
                "Clouds"
            ],
            [
                "Clouds"
            ]
        ],
        "icons": [
            [
                "04n"
            ],
            [
                "04n"
            ],
            [
                "04d"
            ],
            [
                "04d"
            ],
            [
                "04d"
            ],
            [
                "04d"
            ],
            [
                "03d"
            ],
            [
                "04n"
            ]
        ]
    },
    "2024-04-19": {
        "low": [
            72.9,
            74.19,
            74.37,
            74.66,
            75.31,
            75.88,
            75.45,
            74.48
        ],
        "high": [
            72.9,
            74.7,
            74.57,
            74.66,
            75.31,
            75.88,
            75.45,
            74.48
        ],
        "conditions": [
            [
                "Clouds"
            ],
            [
                "Clouds"
            ],
            [
                "Clouds"
            ],
            [
                "Rain"
            ],
            [
                "Clouds"
            ],
            [
                "Clouds"
            ],
            [
                "Clouds"
            ],
            [
                "Clouds"
            ]
        ],
        "icons": [
            [
                "04n"
            ],
            [
                "04n"
            ],
            [
                "04d"
            ],
            [
                "10d"
            ],
            [
                "04d"
            ],
            [
                "03d"
            ],
            [
                "04d"
            ],
            [
                "04n"
            ]
        ]
    },
    "2024-04-20": {
        "low": [
            73.96,
            73.36,
            73.27,
            73.85,
            73.92,
            73.92,
            73.81,
            73.65
        ],
        "high": [
            73.96,
            73.36,
            73.27,
            73.85,
            73.92,
            73.92,
            73.81,
            73.65
        ],
        "conditions": [
            [
                "Clouds"
            ],
            [
                "Clouds"
            ],
            [
                "Clouds"
            ],
            [
                "Clouds"
            ],
            [
                "Clouds"
            ],
            [
                "Rain"
            ],
            [
                "Clouds"
            ],
            [
                "Clouds"
            ]
        ],
        "icons": [
            [
                "04n"
            ],
            [
                "04n"
            ],
            [
                "04d"
            ],
            [
                "04d"
            ],
            [
                "04d"
            ],
            [
                "10d"
            ],
            [
                "04d"
            ],
            [
                "04n"
            ]
        ]
    },
    "2024-04-21": {
        "low": [
            71.73,
            67.95,
            67.03,
            62.29,
            61.66,
            65.8,
            65.77,
            63.3
        ],
        "high": [
            71.73,
            67.95,
            67.03,
            62.29,
            61.66,
            65.8,
            65.77,
            63.3
        ],
        "conditions": [
            [
                "Rain"
            ],
            [
                "Rain"
            ],
            [
                "Rain"
            ],
            [
                "Rain"
            ],
            [
                "Rain"
            ],
            [
                "Clouds"
            ],
            [
                "Clouds"
            ],
            [
                "Clouds"
            ]
        ],
        "icons": [
            [
                "10n"
            ],
            [
                "10n"
            ],
            [
                "10d"
            ],
            [
                "10d"
            ],
            [
                "10d"
            ],
            [
                "04d"
            ],
            [
                "04d"
            ],
            [
                "04n"
            ]
        ]
    },
    "2024-04-22": {
        "low": [
            62.42,
            60.94,
            59.63,
            60.35,
            62.96,
            64.36,
            66.09,
            67.24
        ],
        "high": [
            62.42,
            60.94,
            59.63,
            60.35,
            62.96,
            64.36,
            66.09,
            67.24
        ],
        "conditions": [
            [
                "Clouds"
            ],
            [
                "Clouds"
            ],
            [
                "Clouds"
            ],
            [
                "Clouds"
            ],
            [
                "Clouds"
            ],
            [
                "Clouds"
            ],
            [
                "Clouds"
            ],
            [
                "Clouds"
            ]
        ],
        "icons": [
            [
                "04n"
            ],
            [
                "04n"
            ],
            [
                "04d"
            ],
            [
                "04d"
            ],
            [
                "04d"
            ],
            [
                "04d"
            ],
            [
                "04d"
            ],
            [
                "04n"
            ]
        ]
    },
    "2024-04-23": {
        "low": [
            67.75,
            67.93,
            68.7,
            69.71,
            71.26,
            72.52,
            72.82,
            72.61
        ],
        "high": [
            67.75,
            67.93,
            68.7,
            69.71,
            71.26,
            72.52,
            72.82,
            72.61
        ],
        "conditions": [
            [
                "Clouds"
            ],
            [
                "Clouds"
            ],
            [
                "Rain"
            ],
            [
                "Clouds"
            ],
            [
                "Clouds"
            ],
            [
                "Clouds"
            ],
            [
                "Clouds"
            ],
            [
                "Rain"
            ]
        ],
        "icons": [
            [
                "03n"
            ],
            [
                "02n"
            ],
            [
                "10d"
            ],
            [
                "04d"
            ],
            [
                "04d"
            ],
            [
                "04d"
            ],
            [
                "04d"
            ],
            [
                "10n"
            ]
        ]
    },
    "2024-04-24": {
        "low": [
            73.02,
            null,
            null,
            null,
            null,
            null,
            null,
            null
        ],
        "high": [
            73.02,
            null,
            null,
            null,
            null,
            null,
            null,
            null
        ],
        "conditions": [
            [
                "Clouds"
            ],
            null,
            null,
            null,
            null,
            null,
            null,
            null
        ],
        "icons": [
            [
                "03n"
            ],
            null,
            null,
            null,
            null,
            null,
            null,
            null
        ]
    }
}
